taipy/__init__.py
taipy/gui/__init__.py
taipy/gui/_default_config.py
taipy/gui/_gui_cli.py
taipy/gui/_gui_section.py
taipy/gui/_init.py
taipy/gui/_page.py
taipy/gui/_warnings.py
taipy/gui/config.py
taipy/gui/gui.py
taipy/gui/gui_actions.py
taipy/gui/icon.py
taipy/gui/page.py
taipy/gui/partial.py
taipy/gui/server.py
taipy/gui/state.py
taipy/gui/types.py
taipy/gui/version.json
taipy/gui/viselements.json
taipy/gui/data/__init__.py
taipy/gui/data/array_dict_data_accessor.py
taipy/gui/data/content_accessor.py
taipy/gui/data/data_accessor.py
taipy/gui/data/data_format.py
taipy/gui/data/data_scope.py
taipy/gui/data/numpy_data_accessor.py
taipy/gui/data/pandas_data_accessor.py
taipy/gui/data/utils.py
taipy/gui/data/decimator/__init__.py
taipy/gui/data/decimator/lttb.py
taipy/gui/data/decimator/minmax.py
taipy/gui/data/decimator/rdp.py
taipy/gui/data/decimator/scatter_decimator.py
taipy/gui/extension/__init__.py
taipy/gui/extension/library.py
taipy/gui/renderers/__init__.py
taipy/gui/renderers/builder.py
taipy/gui/renderers/factory.py
taipy/gui/renderers/json.py
taipy/gui/renderers/utils.py
taipy/gui/renderers/_html/__init__.py
taipy/gui/renderers/_html/factory.py
taipy/gui/renderers/_html/parser.py
taipy/gui/renderers/_markdown/__init__.py
taipy/gui/renderers/_markdown/blocproc.py
taipy/gui/renderers/_markdown/control.py
taipy/gui/renderers/_markdown/factory.py
taipy/gui/renderers/_markdown/postproc.py
taipy/gui/renderers/_markdown/preproc.py
taipy/gui/utils/__init__.py
taipy/gui/utils/_adapter.py
taipy/gui/utils/_attributes.py
taipy/gui/utils/_bindings.py
taipy/gui/utils/_evaluator.py
taipy/gui/utils/_locals_context.py
taipy/gui/utils/_map_dict.py
taipy/gui/utils/_runtime_manager.py
taipy/gui/utils/_variable_directory.py
taipy/gui/utils/boolean.py
taipy/gui/utils/chart_config_builder.py
taipy/gui/utils/clientvarname.py
taipy/gui/utils/datatype.py
taipy/gui/utils/date.py
taipy/gui/utils/expr_var_name.py
taipy/gui/utils/filename.py
taipy/gui/utils/filter_locals.py
taipy_gui-2.4.0.dist-info/LICENSE
taipy_gui-2.4.0.dist-info/METADATA
taipy_gui-2.4.0.dist-info/WHEEL
taipy_gui-2.4.0.dist-info/top_level.txt
taipy_gui-2.4.0.dist-info/RECORD
