Metadata-Version: 2.1
Name: taipy-gui
Version: 2.4.0
Summary: Low-code library to create graphical user interfaces on the Web for your Python applications.
Home-page: https://github.com/avaiga/taipy-gui
Author: Avaiga
Author-email: dev@taipy.io
License: Apache License 2.0
Keywords: taipy-gui
Classifier: Intended Audience :: Developers
Classifier: License :: OSI Approved :: Apache Software License
Classifier: Natural Language :: English
Classifier: Programming Language :: Python :: 3
Classifier: Programming Language :: Python :: 3.8
Classifier: Programming Language :: Python :: 3.9
Classifier: Programming Language :: Python :: 3.10
Classifier: Programming Language :: Python :: 3.11
Requires-Python: >=3.8
Provides-Extra: ngrok
Provides-Extra: image
Provides-Extra: arrow
License-File: LICENSE
